pytest_django_docker_pg/VERSION
pytest_django_docker_pg/__init__.py
pytest_django_docker_pg/plugin.py
pytest_django_docker_pg-0.0.4.dist-info/LICENSE
pytest_django_docker_pg-0.0.4.dist-info/METADATA
pytest_django_docker_pg-0.0.4.dist-info/WHEEL
pytest_django_docker_pg-0.0.4.dist-info/entry_points.txt
pytest_django_docker_pg-0.0.4.dist-info/top_level.txt
pytest_django_docker_pg-0.0.4.dist-info/RECORD
